facefusion/__init__.py
facefusion/choices.py
facefusion/common_helper.py
facefusion/config.py
facefusion/content_analyser.py
facefusion/core.py
facefusion/download.py
facefusion/execution.py
facefusion/face_analyser.py
facefusion/face_helper.py
facefusion/face_masker.py
facefusion/face_store.py
facefusion/filesystem.py
facefusion/globals.py
facefusion/logger.py
facefusion/memory.py
facefusion/metadata.py
facefusion/normalizer.py
facefusion/process_manager.py
facefusion/statistics.py
facefusion/typing.py
facefusion/vision.py
facefusion/wording.py
facefusion/processors/__init__.py
facefusion/processors/frame/__init__.py
facefusion/processors/frame/choices.py
facefusion/processors/frame/core.py
facefusion/processors/frame/globals.py
facefusion/processors/frame/typings.py
facefusion/processors/frame/modules/__init__.py
facefusion/processors/frame/modules/face_enhancer.py
facefusion/processors/frame/modules/face_swapper.py
facefusion/processors/frame/modules/frame_enhancer.py
facefusionlib/__init__.py
facefusionlib/swapper.py
facefusionlib-1.1.3.dist-info/LICENSE
facefusionlib-1.1.3.dist-info/METADATA
facefusionlib-1.1.3.dist-info/WHEEL
facefusionlib-1.1.3.dist-info/top_level.txt
facefusionlib-1.1.3.dist-info/RECORD
