Metadata-Version: 2.2
Name: facefusionlib
Version: 1.1.3
Summary: Face swapper and enhancer
Home-page: https://github.com/IAn2018cs/sd-webui-facefusion
Author: IAn2018
Author-email: ian2018cs@gmail.com
Keywords: face,swapper
Classifier: License :: OSI Approved :: MIT License
Classifier: Programming Language :: Python
Classifier: Programming Language :: Python :: 3 :: Only
Classifier: Programming Language :: Python :: 3.9
Classifier: Programming Language :: Python :: 3.10
Classifier: Programming Language :: Python :: 3.11
Classifier: Programming Language :: Python :: 3.12
Requires-Python: >=3.9, <3.13
License-File: LICENSE
Requires-Dist: filetype==1.2.0
Requires-Dist: numpy
Requires-Dist: onnx==1.15.0
Requires-Dist: onnxruntime
Requires-Dist: opencv-python==4.8.1.78
Requires-Dist: realesrgan==0.3.0
Requires-Dist: tqdm
Provides-Extra: gpu
Requires-Dist: onnxruntime-gpu; extra == "gpu"
Dynamic: author
Dynamic: author-email
Dynamic: classifier
Dynamic: description
Dynamic: description-content-type
Dynamic: home-page
Dynamic: keywords
Dynamic: provides-extra
Dynamic: requires-dist
Dynamic: requires-python
Dynamic: summary
